swagger_client/__init__.py
swagger_client/api_client.py
swagger_client/configuration.py
swagger_client/rest.py
swagger_client/api/__init__.py
swagger_client/api/default_api.py
swagger_client/models/__init__.py
swagger_client/models/charge.py
swagger_client/models/consumption.py
swagger_client/models/detailed_product.py
swagger_client/models/extra_product.py
swagger_client/models/extra_product_sample_consumption.py
swagger_client/models/extra_product_sample_consumption_dual_fuel_dual_rate.py
swagger_client/models/extra_product_sample_consumption_dual_fuel_single_rate.py
swagger_client/models/extra_product_sample_consumption_electricity_dual_rate.py
swagger_client/models/extra_product_sample_consumption_electricity_single_rate.py
swagger_client/models/extra_product_sample_quotes.py
swagger_client/models/full_quote.py
swagger_client/models/full_tariff.py
swagger_client/models/inline_response200.py
swagger_client/models/inline_response2001.py
swagger_client/models/inline_response2002.py
swagger_client/models/inline_response2003.py
swagger_client/models/link.py
swagger_client/models/partial_quote.py
swagger_client/models/partial_quote_electricity_dual_rate.py
swagger_client/models/partial_quote_electricity_single_rate.py
swagger_client/models/partial_tariff.py
swagger_client/models/product.py
swagger_client/models/tariffs.py
test/__init__.py
test/test_charge.py
test/test_consumption.py
test/test_default_api.py
test/test_detailed_product.py
test/test_extra_product.py
test/test_extra_product_sample_consumption.py
test/test_extra_product_sample_consumption_dual_fuel_dual_rate.py
test/test_extra_product_sample_consumption_dual_fuel_single_rate.py
test/test_extra_product_sample_consumption_electricity_dual_rate.py
test/test_extra_product_sample_consumption_electricity_single_rate.py
test/test_extra_product_sample_quotes.py
test/test_full_quote.py
test/test_full_tariff.py
test/test_inline_response200.py
test/test_inline_response2001.py
test/test_inline_response2002.py
octopy_api-1.1.0.dist-info/METADATA
octopy_api-1.1.0.dist-info/WHEEL
octopy_api-1.1.0.dist-info/top_level.txt
octopy_api-1.1.0.dist-info/RECORD
